datafiles/__init__.py
datafiles/config.py
datafiles/converters/__init__.py
datafiles/converters/_bases.py
datafiles/converters/builtins.py
datafiles/converters/containers.py
datafiles/converters/enumerations.py
datafiles/converters/extensions.py
datafiles/decorators.py
datafiles/formats.py
datafiles/hooks.py
datafiles/manager.py
datafiles/mapper.py
datafiles/model.py
datafiles/plugins.py
datafiles/py.typed
datafiles/settings.py
datafiles/tests/__init__.py
datafiles/tests/test_converters.py
datafiles/tests/test_decorators.py
datafiles/tests/test_formats.py
datafiles/tests/test_generics.py
datafiles/tests/test_hooks.py
datafiles/tests/test_manager.py
datafiles/tests/test_mapper.py
datafiles/tests/test_model.py
datafiles/tests/test_utils.py
datafiles/types.py
datafiles/utils.py
datafiles-2.5.dist-info/METADATA
datafiles-2.5.dist-info/WHEEL
datafiles-2.5.dist-info/licenses/LICENSE.md
datafiles-2.5.dist-info/RECORD
